{
    "instances": [
        "_PAD_POS", 
        "_ROOT_POS", 
        "_END_POS", 
        "DET", 
        "NOUN", 
        "ADJ", 
        "PUNCT", 
        "PART", 
        "VERB", 
        "PRON", 
        "ADV", 
        "PROPN", 
        "CCONJ", 
        "INTJ", 
        "AUX", 
        "ADP", 
        "NUM", 
        "SCONJ", 
        "X", 
        "SYM"
    ], 
    "instance2index": {
        "ADV": 10, 
        "NOUN": 4, 
        "NUM": 16, 
        "ADP": 15, 
        "PRON": 9, 
        "SCONJ": 17, 
        "PROPN": 11, 
        "DET": 3, 
        "_ROOT_POS": 1, 
        "SYM": 19, 
        "INTJ": 13, 
        "PUNCT": 6, 
        "PART": 7, 
        "_END_POS": 2, 
        "X": 18, 
        "CCONJ": 12, 
        "AUX": 14, 
        "ADJ": 5, 
        "VERB": 8, 
        "_PAD_POS": 0
    }
}