{
    "instance2index": {
        "_PAD_POS": 0,
        "_ROOT_POS": 1,
        "_END_POS": 2,
        "PROPN": 3,
        "AUX": 4,
        "DET": 5,
        "NOUN": 6,
        "PRON": 7,
        "VERB": 8,
        "ADP": 9,
        "PUNCT": 10,
        "ADV": 11,
        "CCONJ": 12,
        "SCONJ": 13,
        "NUM": 14,
        "ADJ": 15,
        "PART": 16,
        "SYM": 17,
        "INTJ": 18,
        "X": 19
    },
    "instances": [
        "_PAD_POS",
        "_ROOT_POS",
        "_END_POS",
        "PROPN",
        "AUX",
        "DET",
        "NOUN",
        "PRON",
        "VERB",
        "ADP",
        "PUNCT",
        "ADV",
        "CCONJ",
        "SCONJ",
        "NUM",
        "ADJ",
        "PART",
        "SYM",
        "INTJ",
        "X"
    ]
}